bunq/__init__.py
bunq/sdk/__init__.py
bunq/sdk/client.py
bunq/sdk/context.py
bunq/sdk/exception.py
bunq/sdk/exception_factory.py
bunq/sdk/security.py
bunq/sdk/json/__init__.py
bunq/sdk/json/adapters.py
bunq/sdk/json/converter.py
bunq/sdk/model/__init__.py
bunq/sdk/model/core.py
bunq/sdk/model/device_server_internal.py
bunq/sdk/model/generated/__init__.py
bunq/sdk/model/generated/endpoint.py
bunq/sdk/model/generated/object_.py
bunq_sdk-0.13.0.dist-info/DESCRIPTION.rst
bunq_sdk-0.13.0.dist-info/METADATA
bunq_sdk-0.13.0.dist-info/RECORD
bunq_sdk-0.13.0.dist-info/WHEEL
bunq_sdk-0.13.0.dist-info/metadata.json
bunq_sdk-0.13.0.dist-info/top_level.txt
tests/http/__init__.py
tests/http/test_api_context.py
tests/http/test_bad_request_with_response_id.py
tests/http/test_pagination.py
tests/http/test_pagination_scenario.py
tests/model/__init__.py
tests/model/generated/__init__.py
tests/model/generated/endpoint/__init__.py
tests/model/generated/endpoint/test_attachment_public.py
tests/model/generated/endpoint/test_avatar.py
tests/model/generated/endpoint/test_card_debit.py
tests/model/generated/endpoint/test_draft_share_invite_bank.py
tests/model/generated/endpoint/test_monetary_account_bank.py
tests/model/generated/endpoint/test_payment.py
tests/model/generated/endpoint/test_request_inquiry.py
tests/model/generated/endpoint/test_session.py
tests/model/generated/endpoint/test_tab_usage_single.py
tests/model/generated/object/__init__.py
tests/model/generated/object/test_notification_url.py
