Metadata-Version: 2.0
Name: bunq-sdk
Version: 0.13.0
Summary: bunq Python SDK
Home-page: https://github.com/bunq/sdk_python
Author: bunq
Author-email: support@bunq.com
License: MIT
Keywords: open-banking sepa bunq finance api payment
Platform: UNKNOWN
Classifier: Development Status :: 4 - Beta
Classifier: Intended Audience :: Developers
Classifier: Topic :: Software Development :: Build Tools
Classifier: License :: OSI Approved :: MIT License
Classifier: Programming Language :: Python :: 3
Classifier: Programming Language :: Python :: 3.3
Classifier: Programming Language :: Python :: 3.4
Classifier: Programming Language :: Python :: 3.5
Classifier: Programming Language :: Python :: 3.6
Requires-Python: >=3
Requires-Dist: aenum (==2.0.8)
Requires-Dist: chardet (==3.0.4)
Requires-Dist: pycryptodomex (==3.4.6)
Requires-Dist: requests (==2.18.1)
Requires-Dist: simplejson (==3.11.1)
Requires-Dist: urllib3 (==1.21.1)
